{"authors": ["Martha Rose Shulman", "Pierre Franey", "Melissa Clark", "Marian Burros", "Kim Severson", "Julia Moskin", "Erin Jeanne Mcdowell", "Genevieve Ko", "Alison Roman", "David Tanis"], "date_download": "2018-11-16 03:36:14", "date_modify": "2018-11-16 03:36:14", "date_publish": "2011-03-15 00:00:00", "description": "When you cook the red onions and broccoli, be sure to heat the pan enough to sear their edges.", "filename": "recipes_1013512-broccoli-and-red-onion-quesadillas_1542339374.html", "image_url": "https://static01.nyt.com/images/2011/03/15/science/15recipehealth/15recipehealth-superJumbo.jpg", "language": "en", "localpath": "/Users/federicoperezinvidio/Projects/illinois/newsfeat/news-please//data/2018/11/16/cooking.nytimes.com/recipes_1013512-broccoli-and-red-onion-quesadillas_1542339374.html", "title": "Broccoli and Red Onion Quesadillas", "title_page": "Broccoli and Red Onion Quesadillas Recipe - NYT Cooking", "title_rss": "NULL", "source_domain": "nytimes.com", "text": "Sorry! We're currently performing maintenance on the site. Certain actions are not working at this time. Check back later.", "url": "https://cooking.nytimes.com/recipes/1013512-broccoli-and-red-onion-quesadillas"}