{"authors": ["Sarah Copeland", "Martha Rose Shulman", "Marian Burros"], "date_download": "2018-11-16 03:32:20", "date_modify": "2018-11-16 03:32:20", "date_publish": null, "description": "Browse and save the best hamburger bun recipes on New York Times Cooking.", "filename": "tag_hamburger%20bun_1542339140.html", "image_url": "https://int.nyt.com/applications/cooking/static/images/NYTCookingLogo.png", "language": "en", "localpath": "/Users/federicoperezinvidio/Projects/illinois/newsfeat/news-please//data/2018/11/16/cooking.nytimes.com/tag_hamburger%20bun_1542339140.html", "title": "Hamburger Bun Recipes", "title_page": "Hamburger Bun Recipes - NYT Cooking", "title_rss": "NULL", "source_domain": "nytimes.com", "text": "Sorry! We're currently performing maintenance on the site. Certain actions are not working at this time. Check back later.", "url": "https://cooking.nytimes.com/tag/hamburger%20bun"}