{"authors": ["Robin Toner", "Adam Nagourney", "Megan Thee", "Dalia Sussman", "Marjorie Connelly"], "date_download": "2018-11-16 03:58:58", "date_modify": "2018-11-16 03:58:58", "date_publish": "2008-09-18 00:00:00", "description": "Recent and archived work by Robin Toner for The New York Times", "filename": "by_robin-toner_1542340738.html", "image_url": "https://static.nytimes.com/images/icons/t_logo_291_black.png", "language": "en", "localpath": "/Users/federicoperezinvidio/Projects/illinois/newsfeat/news-please//data/2018/11/16/nytimes.com/by_robin-toner_1542340738.html", "title": "Robin Toner", "title_page": "Robin Toner", "title_rss": "NULL", "source_domain": "nytimes.com", "text": null, "url": "https://www.nytimes.com/by/robin-toner"}