{"authors": ["Raymond Bonner"], "date_download": "2018-11-16 04:28:01", "date_modify": "2018-11-16 04:28:01", "date_publish": "2014-11-27 00:00:00", "description": "Recent and archived work by Raymond Bonner for The New York Times", "filename": "by_raymond-bonner_1542342481.html", "image_url": "https://static.nytimes.com/images/icons/t_logo_291_black.png", "language": "en", "localpath": "/Users/federicoperezinvidio/Projects/illinois/newsfeat/news-please//data/2018/11/16/nytimes.com/by_raymond-bonner_1542342481.html", "title": "Raymond Bonner", "title_page": "Raymond Bonner", "title_rss": "NULL", "source_domain": "nytimes.com", "text": null, "url": "https://www.nytimes.com/by/raymond-bonner"}