{"authors": [], "date_download": "2018-11-16 03:11:54", "date_modify": "2018-11-16 03:11:54", "date_publish": "2018-10-03 00:00:00", "description": "Sarah Huckabee Sanders, the White House press secretary, deflected criticism of President Trump for mocking Christine Blasey Ford’s testimony, in which she accused Judge Brett Kavanaugh of sexual assault.", "filename": "video_us_politics_100000006142933_sanders-trump-ford.html_playlistId=100000006090324_1542337914.html", "image_url": "https://static01.nyt.com/images/2018/10/03/us/politics/03xp-sanders-facts/03xp-sanders-facts-videoSixteenByNine1050.jpg", "language": "en", "localpath": "/Users/federicoperezinvidio/Projects/illinois/newsfeat/news-please//data/2018/11/16/nytimes.com/video_us_politics_100000006142933_sanders-trump-ford.html_playlistId=100000006090324_1542337914.html", "title": "‘He Was Stating Facts’: Sanders Defends Trump’s Blasey Remarks", "title_page": "‘He Was Stating Facts’: Sanders Defends Trump’s Blasey Remarks - Video - NYTimes.com", "title_rss": "NULL", "source_domain": "nytimes.com", "text": null, "url": "https://www.nytimes.com/video/us/politics/100000006142933/sanders-trump-ford.html?playlistId=100000006090324"}